PyDepManger/__init__.py
PyDepManger/interface.py
PyDepManger-0.1.1.dist-info/METADATA
PyDepManger-0.1.1.dist-info/WHEEL
PyDepManger-0.1.1.dist-info/top_level.txt
PyDepManger-0.1.1.dist-info/RECORD
