Metadata-Version: 2.2
Name: PyDepManger
Version: 0.1.1
Home-page: https://github.com/abuawadd/PyDepManger
Author: Example Author1, Another Author2
Author-email: author2@example.com, another2@example.com
Maintainer: John, Jane
Maintainer-email: john@example.com, jane@example.com
Project-URL: Documentation, https://github.com/abuawadd/PyDepManger/wiki
Project-URL: Source, https://github.com/abuawadd/PyDepManger
Project-URL: Changelog, https://github.com/abuawadd/PyDepManger/blob/main/CHANGELOG.md
Keywords: example,demo,setuptools,package
Classifier: Programming Language :: Python :: 3
Classifier: Operating System :: OS Independent
Classifier: Intended Audience :: Education
Classifier: Intended Audience :: Healthcare Industry
Classifier: Intended Audience :: Science/Research
Classifier: License :: OSI Approved :: GNU General Public License v3 (GPLv3)
Classifier: Programming Language :: Python :: 3.10
Classifier: Programming Language :: Python :: 3.11
Classifier: Programming Language :: Python :: 3.12
Classifier: Programming Language :: Python :: 3.13
Classifier: Programming Language :: C
Classifier: Topic :: Scientific/Engineering :: Bio-Informatics
Requires-Python: >=3.10
Requires-Dist: pandas==2.2.3
Requires-Dist: numpy==2.2.1
Requires-Dist: mlxtend==0.23.3
Requires-Dist: scikit-learn==1.6.1
Requires-Dist: scipy==1.15.0
Requires-Dist: statsmodels==0.14.4
Requires-Dist: joblib==1.4.2
Requires-Dist: tqdm==4.67.1
Requires-Dist: pyarrow==18.1.0
Requires-Dist: pyspark==3.5.4
Dynamic: author
Dynamic: author-email
Dynamic: classifier
Dynamic: description
Dynamic: description-content-type
Dynamic: home-page
Dynamic: keywords
Dynamic: maintainer
Dynamic: maintainer-email
Dynamic: project-url
Dynamic: requires-dist
Dynamic: requires-python
